code_of_ai/__init__.py
code_of_ai/aiallcode.py
code_of_ai-1.2.dist-info/METADATA
code_of_ai-1.2.dist-info/WHEEL
code_of_ai-1.2.dist-info/top_level.txt
code_of_ai-1.2.dist-info/RECORD
