Metadata-Version: 2.1
Name: code_of_ai
Version: 1.2
Summary: all codes available
Author: SY IT
Author-email: your_email@example.com
Classifier: Programming Language :: Python :: 3
Classifier: License :: OSI Approved :: MIT License
Classifier: Operating System :: OS Independent
Requires-Python: >=3.6
